cognitive_schema/__init__.py
cognitive_schema/cli.py
cognitive_schema/query.py
cognitive_schema/db/__init__.py
cognitive_schema/db/download_schema.py
cognitive_schema/db/generate_profiles.py
cognitive_schema-0.2.0.dist-info/LICENSE
cognitive_schema-0.2.0.dist-info/METADATA
cognitive_schema-0.2.0.dist-info/WHEEL
cognitive_schema-0.2.0.dist-info/entry_points.txt
cognitive_schema-0.2.0.dist-info/top_level.txt
cognitive_schema-0.2.0.dist-info/RECORD
